[
  {
    "input": {
      "all articles": " 협업 소프트웨어, 또는 그룹웨어는 여러 사용자가 동시에 하나의 프로젝트를 수행할 수 있도록 하는 소프트웨어이다. 로터스 소프트웨어의 로터스 노츠가 그 대표적인 예시로 손꼽힌다. 이는 사용자들이 각자의 작업 환경에서 협업할 수 있게 해주어 업무 효율성을 높이는데 기여한다. 이러한 협업 소프트웨어의 가치는 점차 증가하고 있으며, 예를 들어 일정 기록의 유용성이 점점 인정받고 있다.  협업 소프트웨어의 확장으로는 협업 미디어가 있다. 협업 미디어는 여러 사용자가 웹사이트 내에서 정보를 생성하고 관리할 수 있는 소프트웨어를 말한다. 이는 위키나 슬래시닷과 같은 플랫폼을 포함한다.  그룹웨어는 커뮤니케이션 도구, 회의 도구, 그리고 협업 관리 도구의 세 가지 범주로 나눌 수 있다. 전자적인 커뮤니케이션 도구는 정보를 주고받을 수 있는 메커니즘을 제공하며, 회의 도구는 상호 작용이 가능한 방식으로 정보를 공유한다. 협업 관리 도구는 그룹 내 활동을 관리하고 조정한다.  협업 소프트웨어는 웹 기반 또는 데스크톱 PC 상에서 실행될 수 있다. 또한, 모바일 사용이 증가함에 따라 모바일 기기에서의 활용도가 높아지고 있다.  협업 소프트웨어는 웹 기반 혹은 소프트웨어 협업 도구로 구분할 수 있으며, 지식 관리 도구, 지식 생성 도구, 정보 공유 도구로 분류할 수도 있다.  협업 소프트웨어를 도입하는 것은 조직 내 변화를 일으키는 과정에서 많은 어려움을 겪을 수 있다. 사람들이 새로운 소프트웨어에 적응하는 것은 시간과 노력이 필요하며, 이를 장려하기 위해 적절한 인센티브가 필요하다.  이러한 소프트웨어는 회사의 사내문화와 잘 맞지 않을 수 있으며, 조직 내에서의 변화를 가져올 때에는 최고경영자를 포함한 모든 단계의 지원이 필요하다.  협업 소프트웨어의 관련 용어로는 컴퓨터 보조 공동 작업이 있으며, 이를 활용한 다양한 응용 프로그램들이 존재한다. 또한, 일반인 기반 공동 생산방식과 같은 개념들도 밀접한 관련이 있다.  협업 소프트웨어의 목록 및 관련 용어들은 소셜 북마크 웹사이트 목록과 같은 목록을 통해 쉽게 찾을 수 있다. 이러한 소프트웨어는 사무용 및 컴퓨터 매개 통신 분야에서 활발히 사용되고 있다.  마지막으로, 협업 소프트웨어의 적용은 기업의 업무 효율성을 향상시키는 데 중요한 역할을 한다. 이를 통해 조직은 경쟁력을 강화하고 사내 협업 문화를 촉진할 수 있다. "
    },
    "output": {
      "snippets": [
        [
          "협업 소프트웨어, 또는 그룹웨어는 여러 사용자가 동시에 하나의 프로젝트를 수행할 수 있도록 하는 소프트웨어이다.",
          "로터스 소프트웨어의 로터스 노츠가 그 대표적인 예시로 손꼽힌다.",
          "이는 사용자들이 각자의 작업 환경에서 협업할 수 있게 해주어 업무 효율성을 높이는데 기여한다."
        ],
        [
          "협업 소프트웨어의 가치는 점차 증가하고 있으며, 예를 들어 일정 기록의 유용성이 점점 인정받고 있다."
        ],
        ["협업 소프트웨어의 확장으로는 협업 미디어가 있다."],
        [
          "협업 미디어는 여러 사용자가 웹사이트 내에서 정보를 생성하고 관리할 수 있는 소프트웨어를 말한다.",
          "이는 위키나 슬래시닷과 같은 플랫폼을 포함한다."
        ],
        [
          "그룹웨어는 커뮤니케이션 도구, 회의 도구, 그리고 협업 관리 도구의 세 가지 범주로 나눌 수 있다."
        ],
        [
          "전자적인 커뮤니케이션 도구는 정보를 주고받을 수 있는 메커니즘을 제공하며, 회의 도구는 상호 작용이 가능한 방식으로 정보를 공유한다."
        ],
        ["협업 관리 도구는 그룹 내 활동을 관리하고 조정한다."],
        ["협업 소프트웨어는 웹 기반 또는 데스크톱 PC 상에서 실행될 수 있다."],
        [
          "모바일 사용이 증가함에 따라 모바일 기기에서의 활용도가 높아지고 있다."
        ],
        [
          "협업 소프트웨어는 웹 기반 혹은 소프트웨어 협업 도구로 구분할 수 있으며, 지식 관리 도구, 지식 생성 도구, 정보 공유 도구로 분류할 수도 있다."
        ],
        [
          "협업 소프트웨어를 도입하는 것은 조직 내 변화를 일으키는 과정에서 많은 어려움을 겪을 수 있다."
        ],
        [
          "사람들이 새로운 소프트웨어에 적응하는 것은 시간과 노력이 필요하며, 이를 장려하기 위해 적절한 인센티브가 필요하다.",
          "이러한 소프트웨어는 회사의 사내문화와 잘 맞지 않을 수 있으며, 조직 내에서의 변화를 가져올 때에는 최고경영자를 포함한 모든 단계의 지원이 필요하다."
        ],
        [
          "협업 소프트웨어의 관련 용어로는 컴퓨터 보조 공동 작업이 있으며, 이를 활용한 다양한 응용 프로그램들이 존재한다.",
          "또한, 일반인 기반 공동 생산방식과 같은 개념들도 밀접한 관련이 있다."
        ],
        [
          "협업 소프트웨어의 목록 및 관련 용어들은 소셜 북마크 웹사이트 목록과 같은 목록을 통해 쉽게 찾을 수 있다.",
          "이러한 소프트웨어는 사무용 및 컴퓨터 매개 통신 분야에서 활발히 사용되고 있다."
        ],
        [
          "마지막으로, 협업 소프트웨어의 적용은 기업의 업무 효율성을 향상시키는 데 중요한 역할을 한다.",
          "이를 통해 조직은 경쟁력을 강화하고 사내 협업 문화를 촉진할 수 있다."
        ]
      ],
      "all contents": {
        "협업 소프트웨어의 정의": [
          "협업 소프트웨어, 또는 그룹웨어는 여러 사용자가 동시에 하나의 프로젝트를 수행할 수 있도록 하는 소프트웨어이다."
        ],
        "대표적인 예시": [
          "로터스 소프트웨어의 로터스 노츠가 그 대표적인 예시로 손꼽힌다."
        ],
        "기여하는 가치": [
          "이는 사용자들이 각자의 작업 환경에서 협업할 수 있게 해주어 업무 효율성을 높이는데 기여한다.",
          "협업 소프트웨어의 가치는 점차 증가하고 있으며, 예를 들어 일정 기록의 유용성이 점점 인정받고 있다."
        ],
        "확장 개념": {
          "협업 미디어": [
            "협업 소프트웨어의 확장으로는 협업 미디어가 있다.",
            "협업 미디어는 여러 사용자가 웹사이트 내에서 정보를 생성하고 관리할 수 있는 소프트웨어를 말한다.",
            "이는 위키나 슬래시닷과 같은 플랫폼을 포함한다."
          ]
        },
        "그룹웨어의 구성": [
          "그룹웨어는 커뮤니케이션 도구, 회의 도구, 그리고 협업 관리 도구의 세 가지 범주로 나눌 수 있다.",
          "전자적인 커뮤니케이션 도구는 정보를 주고받을 수 있는 메커니즘을 제공하며, 회의 도구는 상호 작용이 가능한 방식으로 정보를 공유한다.",
          "협업 관리 도구는 그룹 내 활동을 관리하고 조정한다."
        ],
        "사용 플랫폼": [
          "협업 소프트웨어는 웹 기반 또는 데스크톱 PC 상에서 실행될 수 있다.",
          "모바일 사용이 증가함에 따라 모바일 기기에서의 활용도가 높아지고 있다."
        ],
        "소프트웨어 분류": [
          "협업 소프트웨어는 웹 기반 혹은 소프트웨어 협업 도구로 구분할 수 있으며, 지식 관리 도구, 지식 생성 도구, 정보 공유 도구로 분류할 수도 있다."
        ],
        "도입 시 고려사항": [
          "협업 소프트웨어를 도입하는 것은 조직 내 변화를 일으키는 과정에서 많은 어려움을 겪을 수 있다.",
          "사람들이 새로운 소프트웨어에 적응하는 것은 시간과 노력이 필요하며, 이를 장려하기 위해 적절한 인센티브가 필요하다.",
          "이러한 소프트웨어는 회사의 사내문화와 잘 맞지 않을 수 있으며, 조직 내에서의 변화를 가져올 때에는 최고경영자를 포함한 모든 단계의 지원이 필요하다."
        ],
        "관련 용어 및 응용": [
          "협업 소프트웨어의 관련 용어로는 컴퓨터 보조 공동 작업이 있으며, 이를 활용한 다양한 응용 프로그램들이 존재한다.",
          "또한, 일반인 기반 공동 생산방식과 같은 개념들도 밀접한 관련이 있다."
        ],
        "소프트웨어 목록과 사용 분야": [
          "협업 소프트웨어의 목록 및 관련 용어들은 소셜 북마크 웹사이트 목록과 같은 목록을 통해 쉽게 찾을 수 있다.",
          "이러한 소프트웨어는 사무용 및 컴퓨터 매개 통신 분야에서 활발히 사용되고 있다."
        ],
        "업무 효율성 향상 및 사내 협업 문화": [
          "마지막으로, 협업 소프트웨어의 적용은 기업의 업무 효율성을 향상시키는 데 중요한 역할을 한다.",
          "이를 통해 조직은 경쟁력을 강화하고 사내 협업 문화를 촉진할 수 있다."
        ]
      }
    }
  }
]
